{
  "quotes": [
    {
      "Date": "2023-10-27 01:36",
      "Rate": "18.1184"
    },
    {
      "Date": "2023-10-27 01:40",
      "Rate": "18.1143"
    },
    {
      "Date": "2023-10-27 01:47",
      "Rate": "18.1113"
    },
    {
      "Date": "2023-10-27 01:50",
      "Rate": "18.1144"
    },
    {
      "Date": "2023-10-27 01:56",
      "Rate": "18.0999"
    },
    {
      "Date": "2023-10-27 02:02",
      "Rate": "18.0999"
    },
    {
      "Date": "2023-10-27 02:06",
      "Rate": "18.0961"
    },
    {
      "Date": "2023-10-27 02:11",
      "Rate": "18.0929"
    },
    {
      "Date": "2023-10-27 02:17",
      "Rate": "18.0945"
    },
    {
      "Date": "2023-10-27 02:21",
      "Rate": "18.1077"
    },
    {
      "Date": "2023-10-27 02:27",
      "Rate": "18.0987"
    },
    {
      "Date": "2023-10-27 02:31",
      "Rate": "18.0943"
    },
    {
      "Date": "2023-10-27 02:36",
      "Rate": "18.0933"
    },
    {
      "Date": "2023-10-27 02:40",
      "Rate": "18.0943"
    },
    {
      "Date": "2023-10-27 02:46",
      "Rate": "18.0904"
    },
    {
      "Date": "2023-10-27 02:52",
      "Rate": "18.0904"
    },
    {
      "Date": "2023-10-27 02:56",
      "Rate": "18.0897"
    },
    {
      "Date": "2023-10-27 03:01",
      "Rate": "18.0773"
    },
    {
      "Date": "2023-10-27 03:07",
      "Rate": "18.0782"
    },
    {
      "Date": "2023-10-27 03:11",
      "Rate": "18.0805"
    },
    {
      "Date": "2023-10-27 03:17",
      "Rate": "18.0850"
    },
    {
      "Date": "2023-10-27 03:22",
      "Rate": "18.0763"
    },
    {
      "Date": "2023-10-27 03:25",
      "Rate": "18.0799"
    },
    {
      "Date": "2023-10-27 03:31",
      "Rate": "18.0799"
    },
    {
      "Date": "2023-10-27 03:37",
      "Rate": "18.0827"
    },
    {
      "Date": "2023-10-27 03:41",
      "Rate": "18.0827"
    },
    {
      "Date": "2023-10-27 03:47",
      "Rate": "18.0834"
    },
    {
      "Date": "2023-10-27 03:52",
      "Rate": "18.0834"
    },
    {
      "Date": "2023-10-27 03:56",
      "Rate": "18.0829"
    },
    {
      "Date": "2023-10-27 04:02",
      "Rate": "18.0804"
    },
    {
      "Date": "2023-10-27 04:07",
      "Rate": "18.0903"
    },
    {
      "Date": "2023-10-27 04:12",
      "Rate": "18.0903"
    },
    {
      "Date": "2023-10-27 04:17",
      "Rate": "18.1205"
    },
    {
      "Date": "2023-10-27 04:22",
      "Rate": "18.1205"
    },
    {
      "Date": "2023-10-27 04:27",
      "Rate": "18.0938"
    },
    {
      "Date": "2023-10-27 04:32",
      "Rate": "18.1004"
    },
    {
      "Date": "2023-10-27 04:37",
      "Rate": "18.1168"
    },
    {
      "Date": "2023-10-27 04:41",
      "Rate": "18.1096"
    },
    {
      "Date": "2023-10-27 04:47",
      "Rate": "18.1034"
    },
    {
      "Date": "2023-10-27 04:51",
      "Rate": "18.1096"
    },
    {
      "Date": "2023-10-27 04:55",
      "Rate": "18.1149"
    },
    {
      "Date": "2023-10-27 05:02",
      "Rate": "18.1258"
    },
    {
      "Date": "2023-10-27 05:07",
      "Rate": "18.1095"
    },
    {
      "Date": "2023-10-27 05:12",
      "Rate": "18.0915"
    },
    {
      "Date": "2023-10-27 05:17",
      "Rate": "18.0869"
    },
    {
      "Date": "2023-10-27 05:21",
      "Rate": "18.0692"
    },
    {
      "Date": "2023-10-27 05:26",
      "Rate": "18.0726"
    },
    {
      "Date": "2023-10-27 05:32",
      "Rate": "18.0930"
    },
    {
      "Date": "2023-10-27 05:36",
      "Rate": "18.0809"
    },
    {
      "Date": "2023-10-27 05:42",
      "Rate": "18.0656"
    },
    {
      "Date": "2023-10-27 05:47",
      "Rate": "18.0605"
    },
    {
      "Date": "2023-10-27 05:50",
      "Rate": "18.0577"
    },
    {
      "Date": "2023-10-27 05:56",
      "Rate": "18.0297"
    },
    {
      "Date": "2023-10-27 06:02",
      "Rate": "18.0297"
    },
    {
      "Date": "2023-10-27 06:07",
      "Rate": "18.0340"
    },
    {
      "Date": "2023-10-27 06:12",
      "Rate": "18.0042"
    },
    {
      "Date": "2023-10-27 06:16",
      "Rate": "18.0041"
    },
    {
      "Date": "2023-10-27 06:20",
      "Rate": "18.0248"
    },
    {
      "Date": "2023-10-27 06:25",
      "Rate": "18.0248"
    },
    {
      "Date": "2023-10-27 06:32",
      "Rate": "18.0123"
    },
    {
      "Date": "2023-10-27 06:37",
      "Rate": "18.0017"
    },
    {
      "Date": "2023-10-27 06:40",
      "Rate": "18.0185"
    },
    {
      "Date": "2023-10-27 06:45",
      "Rate": "18.0346"
    },
    {
      "Date": "2023-10-27 06:50",
      "Rate": "18.0339"
    },
    {
      "Date": "2023-10-27 06:56",
      "Rate": "18.0400"
    },
    {
      "Date": "2023-10-27 07:00",
      "Rate": "18.0546"
    },
    {
      "Date": "2023-10-27 07:05",
      "Rate": "18.0400"
    },
    {
      "Date": "2023-10-27 07:10",
      "Rate": "18.0521"
    },
    {
      "Date": "2023-10-27 07:15",
      "Rate": "18.0653"
    },
    {
      "Date": "2023-10-27 07:20",
      "Rate": "18.0589"
    },
    {
      "Date": "2023-10-27 07:25",
      "Rate": "18.0589"
    },
    {
      "Date": "2023-10-27 07:31",
      "Rate": "18.0547"
    },
    {
      "Date": "2023-10-27 07:35",
      "Rate": "18.0659"
    },
    {
      "Date": "2023-10-27 07:41",
      "Rate": "18.0748"
    },
    {
      "Date": "2023-10-27 07:45",
      "Rate": "18.0659"
    },
    {
      "Date": "2023-10-27 07:50",
      "Rate": "18.0863"
    },
    {
      "Date": "2023-10-27 07:55",
      "Rate": "18.0764"
    },
    {
      "Date": "2023-10-27 08:01",
      "Rate": "18.0639"
    },
    {
      "Date": "2023-10-27 08:05",
      "Rate": "18.0728"
    },
    {
      "Date": "2023-10-27 08:10",
      "Rate": "18.0470"
    },
    {
      "Date": "2023-10-27 08:15",
      "Rate": "18.0438"
    },
    {
      "Date": "2023-10-27 08:20",
      "Rate": "18.0454"
    },
    {
      "Date": "2023-10-27 08:25",
      "Rate": "18.0553"
    },
    {
      "Date": "2023-10-27 08:30",
      "Rate": "18.0553"
    },
    {
      "Date": "2023-10-27 08:35",
      "Rate": "18.0415"
    },
    {
      "Date": "2023-10-27 08:40",
      "Rate": "18.0479"
    },
    {
      "Date": "2023-10-27 08:45",
      "Rate": "18.0343"
    },
    {
      "Date": "2023-10-27 08:50",
      "Rate": "18.0343"
    },
    {
      "Date": "2023-10-27 08:55",
      "Rate": "18.0374"
    },
    {
      "Date": "2023-10-27 09:00",
      "Rate": "18.0437"
    },
    {
      "Date": "2023-10-27 09:05",
      "Rate": "18.0437"
    },
    {
      "Date": "2023-10-27 09:10",
      "Rate": "18.0502"
    },
    {
      "Date": "2023-10-27 09:15",
      "Rate": "18.0579"
    },
    {
      "Date": "2023-10-27 09:20",
      "Rate": "18.0561"
    },
    {
      "Date": "2023-10-27 09:25",
      "Rate": "18.0477"
    },
    {
      "Date": "2023-10-27 09:30",
      "Rate": "18.0574"
    },
    {
      "Date": "2023-10-27 09:35",
      "Rate": "18.0477"
    },
    {
      "Date": "2023-10-27 09:40",
      "Rate": "18.0507"
    },
    {
      "Date": "2023-10-27 09:45",
      "Rate": "18.0544"
    },
    {
      "Date": "2023-10-27 09:51",
      "Rate": "18.0580"
    },
    {
      "Date": "2023-10-27 09:55",
      "Rate": "18.0642"
    },
    {
      "Date": "2023-10-27 10:00",
      "Rate": "18.0650"
    },
    {
      "Date": "2023-10-27 10:05",
      "Rate": "18.0734"
    },
    {
      "Date": "2023-10-27 10:10",
      "Rate": "18.0734"
    },
    {
      "Date": "2023-10-27 10:15",
      "Rate": "18.1042"
    },
    {
      "Date": "2023-10-27 10:20",
      "Rate": "18.1025"
    },
    {
      "Date": "2023-10-27 10:25",
      "Rate": "18.0960"
    },
    {
      "Date": "2023-10-27 10:30",
      "Rate": "18.0956"
    },
    {
      "Date": "2023-10-27 10:35",
      "Rate": "18.0960"
    },
    {
      "Date": "2023-10-27 10:41",
      "Rate": "18.1088"
    },
    {
      "Date": "2023-10-27 10:45",
      "Rate": "18.1169"
    },
    {
      "Date": "2023-10-27 10:50",
      "Rate": "18.1088"
    },
    {
      "Date": "2023-10-27 10:55",
      "Rate": "18.1169"
    },
    {
      "Date": "2023-10-27 11:01",
      "Rate": "18.1082"
    },
    {
      "Date": "2023-10-27 11:05",
      "Rate": "18.1033"
    },
    {
      "Date": "2023-10-27 11:10",
      "Rate": "18.1096"
    },
    {
      "Date": "2023-10-27 11:15",
      "Rate": "18.1033"
    },
    {
      "Date": "2023-10-27 11:20",
      "Rate": "18.1096"
    },
    {
      "Date": "2023-10-27 11:25",
      "Rate": "18.1029"
    },
    {
      "Date": "2023-10-27 11:31",
      "Rate": "18.1020"
    },
    {
      "Date": "2023-10-27 11:35",
      "Rate": "18.1029"
    },
    {
      "Date": "2023-10-27 11:40",
      "Rate": "18.1034"
    },
    {
      "Date": "2023-10-27 11:45",
      "Rate": "18.1088"
    },
    {
      "Date": "2023-10-27 11:50",
      "Rate": "18.1008"
    },
    {
      "Date": "2023-10-27 11:55",
      "Rate": "18.1115"
    },
    {
      "Date": "2023-10-27 12:00",
      "Rate": "18.1115"
    },
    {
      "Date": "2023-10-27 12:05",
      "Rate": "18.1115"
    },
    {
      "Date": "2023-10-27 12:10",
      "Rate": "18.1047"
    },
    {
      "Date": "2023-10-27 12:15",
      "Rate": "18.1038"
    },
    {
      "Date": "2023-10-27 12:20",
      "Rate": "18.0971"
    },
    {
      "Date": "2023-10-27 12:25",
      "Rate": "18.1047"
    },
    {
      "Date": "2023-10-27 12:30",
      "Rate": "18.1048"
    },
    {
      "Date": "2023-10-27 12:35",
      "Rate": "18.1048"
    },
    {
      "Date": "2023-10-27 12:40",
      "Rate": "18.1069"
    },
    {
      "Date": "2023-10-27 12:45",
      "Rate": "18.1126"
    },
    {
      "Date": "2023-10-27 12:50",
      "Rate": "18.1099"
    },
    {
      "Date": "2023-10-27 12:55",
      "Rate": "18.1067"
    },
    {
      "Date": "2023-10-27 13:00",
      "Rate": "18.1111"
    },
    {
      "Date": "2023-10-27 13:05",
      "Rate": "18.1111"
    },
    {
      "Date": "2023-10-27 13:10",
      "Rate": "18.1069"
    },
    {
      "Date": "2023-10-27 13:15",
      "Rate": "18.1069"
    },
    {
      "Date": "2023-10-27 13:20",
      "Rate": "18.1018"
    },
    {
      "Date": "2023-10-27 13:25",
      "Rate": "18.1050"
    },
    {
      "Date": "2023-10-27 13:30",
      "Rate": "18.1018"
    },
    {
      "Date": "2023-10-27 13:36",
      "Rate": "18.1120"
    },
    {
      "Date": "2023-10-27 13:41",
      "Rate": "18.1140"
    },
    {
      "Date": "2023-10-27 13:45",
      "Rate": "18.1140"
    },
    {
      "Date": "2023-10-27 13:50",
      "Rate": "18.1198"
    },
    {
      "Date": "2023-10-27 13:55",
      "Rate": "18.1198"
    },
    {
      "Date": "2023-10-29 15:50",
      "Rate": "18.1061"
    },
    {
      "Date": "2023-10-29 15:55",
      "Rate": "18.1061"
    },
    {
      "Date": "2023-10-29 16:00",
      "Rate": "18.1028"
    },
    {
      "Date": "2023-10-29 16:05",
      "Rate": "18.1030"
    },
    {
      "Date": "2023-10-29 16:10",
      "Rate": "18.1063"
    },
    {
      "Date": "2023-10-29 16:16",
      "Rate": "18.1088"
    },
    {
      "Date": "2023-10-29 16:20",
      "Rate": "18.1088"
    },
    {
      "Date": "2023-10-29 16:25",
      "Rate": "18.1088"
    },
    {
      "Date": "2023-10-29 16:30",
      "Rate": "18.1083"
    },
    {
      "Date": "2023-10-29 16:36",
      "Rate": "18.1083"
    },
    {
      "Date": "2023-10-29 16:40",
      "Rate": "18.1109"
    },
    {
      "Date": "2023-10-29 16:45",
      "Rate": "18.1113"
    },
    {
      "Date": "2023-10-29 16:50",
      "Rate": "18.1080"
    },
    {
      "Date": "2023-10-29 16:55",
      "Rate": "18.1058"
    },
    {
      "Date": "2023-10-29 17:00",
      "Rate": "18.1064"
    },
    {
      "Date": "2023-10-29 17:05",
      "Rate": "18.1103"
    },
    {
      "Date": "2023-10-29 17:10",
      "Rate": "18.1103"
    },
    {
      "Date": "2023-10-29 17:16",
      "Rate": "18.1041"
    },
    {
      "Date": "2023-10-29 17:20",
      "Rate": "18.1040"
    },
    {
      "Date": "2023-10-29 17:25",
      "Rate": "18.1037"
    },
    {
      "Date": "2023-10-29 17:30",
      "Rate": "18.1037"
    },
    {
      "Date": "2023-10-29 17:36",
      "Rate": "18.1039"
    },
    {
      "Date": "2023-10-29 17:40",
      "Rate": "18.1051"
    },
    {
      "Date": "2023-10-29 17:45",
      "Rate": "18.1007"
    },
    {
      "Date": "2023-10-29 17:50",
      "Rate": "18.1019"
    },
    {
      "Date": "2023-10-29 17:55",
      "Rate": "18.1019"
    },
    {
      "Date": "2023-10-29 18:00",
      "Rate": "18.1024"
    },
    {
      "Date": "2023-10-29 18:05",
      "Rate": "18.0988"
    },
    {
      "Date": "2023-10-29 18:10",
      "Rate": "18.0971"
    },
    {
      "Date": "2023-10-29 18:15",
      "Rate": "18.0958"
    },
    {
      "Date": "2023-10-29 18:20",
      "Rate": "18.1053"
    },
    {
      "Date": "2023-10-29 18:25",
      "Rate": "18.1069"
    },
    {
      "Date": "2023-10-29 18:30",
      "Rate": "18.1058"
    },
    {
      "Date": "2023-10-29 18:36",
      "Rate": "18.1031"
    },
    {
      "Date": "2023-10-29 18:40",
      "Rate": "18.1001"
    },
    {
      "Date": "2023-10-29 18:46",
      "Rate": "18.1031"
    },
    {
      "Date": "2023-10-29 18:50",
      "Rate": "18.0938"
    },
    {
      "Date": "2023-10-29 18:55",
      "Rate": "18.0958"
    },
    {
      "Date": "2023-10-29 19:00",
      "Rate": "18.0947"
    },
    {
      "Date": "2023-10-29 19:06",
      "Rate": "18.0956"
    },
    {
      "Date": "2023-10-29 19:10",
      "Rate": "18.0886"
    },
    {
      "Date": "2023-10-29 19:15",
      "Rate": "18.0926"
    },
    {
      "Date": "2023-10-29 19:20",
      "Rate": "18.0950"
    },
    {
      "Date": "2023-10-29 19:25",
      "Rate": "18.0946"
    },
    {
      "Date": "2023-10-29 19:30",
      "Rate": "18.0950"
    },
    {
      "Date": "2023-10-29 19:35",
      "Rate": "18.0949"
    },
    {
      "Date": "2023-10-29 19:41",
      "Rate": "18.0947"
    },
    {
      "Date": "2023-10-29 19:46",
      "Rate": "18.0957"
    },
    {
      "Date": "2023-10-29 19:50",
      "Rate": "18.0957"
    },
    {
      "Date": "2023-10-29 19:55",
      "Rate": "18.0954"
    },
    {
      "Date": "2023-10-29 20:00",
      "Rate": "18.0949"
    },
    {
      "Date": "2023-10-29 20:06",
      "Rate": "18.0949"
    },
    {
      "Date": "2023-10-29 20:10",
      "Rate": "18.0975"
    },
    {
      "Date": "2023-10-29 20:15",
      "Rate": "18.0947"
    },
    {
      "Date": "2023-10-29 20:20",
      "Rate": "18.0947"
    },
    {
      "Date": "2023-10-29 20:25",
      "Rate": "18.0947"
    },
    {
      "Date": "2023-10-29 20:30",
      "Rate": "18.0972"
    },
    {
      "Date": "2023-10-29 20:35",
      "Rate": "18.0941"
    },
    {
      "Date": "2023-10-29 20:40",
      "Rate": "18.0918"
    },
    {
      "Date": "2023-10-29 20:46",
      "Rate": "18.0877"
    },
    {
      "Date": "2023-10-29 20:50",
      "Rate": "18.0877"
    },
    {
      "Date": "2023-10-29 20:55",
      "Rate": "18.0877"
    },
    {
      "Date": "2023-10-29 21:00",
      "Rate": "18.0883"
    },
    {
      "Date": "2023-10-29 21:05",
      "Rate": "18.0895"
    },
    {
      "Date": "2023-10-29 21:10",
      "Rate": "18.0883"
    },
    {
      "Date": "2023-10-29 21:15",
      "Rate": "18.0888"
    },
    {
      "Date": "2023-10-29 21:20",
      "Rate": "18.0944"
    },
    {
      "Date": "2023-10-29 21:25",
      "Rate": "18.0938"
    },
    {
      "Date": "2023-10-29 21:30",
      "Rate": "18.0947"
    },
    {
      "Date": "2023-10-29 21:35",
      "Rate": "18.0938"
    },
    {
      "Date": "2023-10-29 21:40",
      "Rate": "18.0969"
    },
    {
      "Date": "2023-10-29 21:45",
      "Rate": "18.0956"
    },
    {
      "Date": "2023-10-29 21:50",
      "Rate": "18.0957"
    },
    {
      "Date": "2023-10-29 21:55",
      "Rate": "18.1000"
    },
    {
      "Date": "2023-10-29 22:00",
      "Rate": "18.1015"
    },
    {
      "Date": "2023-10-29 22:05",
      "Rate": "18.1001"
    },
    {
      "Date": "2023-10-29 22:10",
      "Rate": "18.1001"
    },
    {
      "Date": "2023-10-29 22:15",
      "Rate": "18.1018"
    },
    {
      "Date": "2023-10-29 22:20",
      "Rate": "18.0984"
    },
    {
      "Date": "2023-10-29 22:25",
      "Rate": "18.0978"
    },
    {
      "Date": "2023-10-29 22:30",
      "Rate": "18.0936"
    },
    {
      "Date": "2023-10-29 22:35",
      "Rate": "18.0961"
    },
    {
      "Date": "2023-10-29 22:41",
      "Rate": "18.0990"
    },
    {
      "Date": "2023-10-29 22:46",
      "Rate": "18.1012"
    },
    {
      "Date": "2023-10-29 22:50",
      "Rate": "18.0981"
    },
    {
      "Date": "2023-10-29 22:55",
      "Rate": "18.0982"
    },
    {
      "Date": "2023-10-29 23:00",
      "Rate": "18.0988"
    },
    {
      "Date": "2023-10-29 23:05",
      "Rate": "18.0982"
    },
    {
      "Date": "2023-10-29 23:10",
      "Rate": "18.0988"
    },
    {
      "Date": "2023-10-29 23:15",
      "Rate": "18.0927"
    },
    {
      "Date": "2023-10-29 23:20",
      "Rate": "18.0891"
    },
    {
      "Date": "2023-10-29 23:25",
      "Rate": "18.0897"
    },
    {
      "Date": "2023-10-29 23:30",
      "Rate": "18.0891"
    },
    {
      "Date": "2023-10-29 23:35",
      "Rate": "18.0896"
    },
    {
      "Date": "2023-10-29 23:40",
      "Rate": "18.0896"
    },
    {
      "Date": "2023-10-29 23:45",
      "Rate": "18.0896"
    },
    {
      "Date": "2023-10-29 23:50",
      "Rate": "18.0850"
    },
    {
      "Date": "2023-10-29 23:56",
      "Rate": "18.0867"
    },
    {
      "Date": "2023-10-30 00:00",
      "Rate": "18.0832"
    },
    {
      "Date": "2023-10-30 00:05",
      "Rate": "18.0801"
    },
    {
      "Date": "2023-10-30 00:10",
      "Rate": "18.0832"
    },
    {
      "Date": "2023-10-30 00:15",
      "Rate": "18.0762"
    },
    {
      "Date": "2023-10-30 00:20",
      "Rate": "18.0743"
    },
    {
      "Date": "2023-10-30 00:25",
      "Rate": "18.0719"
    },
    {
      "Date": "2023-10-30 00:30",
      "Rate": "18.0770"
    },
    {
      "Date": "2023-10-30 00:35",
      "Rate": "18.0817"
    },
    {
      "Date": "2023-10-30 00:40",
      "Rate": "18.0858"
    },
    {
      "Date": "2023-10-30 00:45",
      "Rate": "18.0859"
    },
    {
      "Date": "2023-10-30 00:50",
      "Rate": "18.0845"
    },
    {
      "Date": "2023-10-30 00:55",
      "Rate": "18.0839"
    },
    {
      "Date": "2023-10-30 01:01",
      "Rate": "18.0889"
    },
    {
      "Date": "2023-10-30 01:05",
      "Rate": "18.0768"
    },
    {
      "Date": "2023-10-30 01:10",
      "Rate": "18.0700"
    },
    {
      "Date": "2023-10-30 01:15",
      "Rate": "18.0650"
    },
    {
      "Date": "2023-10-30 01:20",
      "Rate": "18.0603"
    },
    {
      "Date": "2023-10-30 01:25",
      "Rate": "18.0603"
    },
    {
      "Date": "2023-10-30 01:30",
      "Rate": "18.0657"
    },
    {
      "Date": "2023-10-30 01:35",
      "Rate": "18.0633"
    },
    {
      "Date": "2023-10-30 01:40",
      "Rate": "18.0633"
    },
    {
      "Date": "2023-10-30 01:45",
      "Rate": "18.0642"
    },
    {
      "Date": "2023-10-30 01:50",
      "Rate": "18.0651"
    },
    {
      "Date": "2023-10-30 01:55",
      "Rate": "18.0619"
    },
    {
      "Date": "2023-10-30 02:00",
      "Rate": "18.0543"
    },
    {
      "Date": "2023-10-30 02:05",
      "Rate": "18.0503"
    },
    {
      "Date": "2023-10-30 02:10",
      "Rate": "18.0543"
    },
    {
      "Date": "2023-10-30 02:15",
      "Rate": "18.0366"
    },
    {
      "Date": "2023-10-30 02:20",
      "Rate": "18.0277"
    },
    {
      "Date": "2023-10-30 02:25",
      "Rate": "18.0198"
    },
    {
      "Date": "2023-10-30 02:30",
      "Rate": "18.0156"
    },
    {
      "Date": "2023-10-30 02:35",
      "Rate": "18.0198"
    },
    {
      "Date": "2023-10-30 02:40",
      "Rate": "18.0223"
    },
    {
      "Date": "2023-10-30 02:45",
      "Rate": "18.0210"
    },
    {
      "Date": "2023-10-30 02:50",
      "Rate": "18.0210"
    },
    {
      "Date": "2023-10-30 02:55",
      "Rate": "18.0146"
    },
    {
      "Date": "2023-10-30 03:00",
      "Rate": "18.0185"
    },
    {
      "Date": "2023-10-30 03:05",
      "Rate": "18.0164"
    },
    {
      "Date": "2023-10-30 03:10",
      "Rate": "18.0101"
    },
    {
      "Date": "2023-10-30 03:15",
      "Rate": "18.0220"
    },
    {
      "Date": "2023-10-30 03:20",
      "Rate": "18.0220"
    },
    {
      "Date": "2023-10-30 03:25",
      "Rate": "18.0393"
    }
  ]
}